README.md
setup.py
arcgisUtils/__init__.py
arcgisUtils/__main__.py
arcgisUtils/viewer.py
arcgisUtils/vizzuality.py
arcgisUtils.egg-info/PKG-INFO
arcgisUtils.egg-info/SOURCES.txt
arcgisUtils.egg-info/dependency_links.txt
arcgisUtils.egg-info/entry_points.txt
arcgisUtils.egg-info/requires.txt
arcgisUtils.egg-info/top_level.txt