Metadata-Version: 2.1
Name: arcgisUtils
Version: 0.0.1
Summary: Functions to interact with the api in arcgis online.
Home-page: https://github.com/vizzTools/arcgisUtils
Author: Vizzuality
Author-email: greta.carrete@vizzuality.com
License: MIT
Platform: UNKNOWN
Classifier: License :: OSI Approved :: MIT License
Classifier: Programming Language :: Python :: 3
Classifier: Programming Language :: Python :: 3.7
Classifier: Operating System :: OS Independent
